MANIFEST.in
README.txt
setup.py
kellyvector.egg-info/PKG-INFO
kellyvector.egg-info/SOURCES.txt
kellyvector.egg-info/dependency_links.txt
kellyvector.egg-info/top_level.txt
scr/__init__.py