Metadata-Version: 1.1
Name: kellyvector
Version: 0.0.1
Summary: Module for multi-dimentional vector calculations
Home-page: UNKNOWN
Author: Giorgio Abbadessa
Author-email: gio.abbadessa@gmail.com
License: MIT
Keywords: vector
Platform: UNKNOWN
Classifier: License :: OSI Approved :: MIT License
Classifier: Programming Language :: Python :: 3
Classifier: Operating System :: OS Independent
